pintes/__init__.py
pintes/javascript.py
pintes-0.6b0.dist-info/METADATA
pintes-0.6b0.dist-info/WHEEL
pintes-0.6b0.dist-info/licenses/LICENSE
pintes-0.6b0.dist-info/RECORD
