Metadata-Version: 2.4
Name: pintes
Version: 0.6b0
Summary: A Python-based static HTML page generator similar to TKinter.
Project-URL: Issues, https://github.com/FormunaGit/Pintes/issues
Project-URL: Source, https://github.com/FormunaGit/Pintes
Author: Formuna
License-Expression: GPL-3.0-or-later
License-File: LICENSE
Keywords: generator,html,tkinter
Classifier: Development Status :: 4 - Beta
Classifier: License :: OSI Approved :: GNU General Public License v3 (GPLv3)
Classifier: Operating System :: OS Independent
Classifier: Programming Language :: Python :: 3
Requires-Python: >=3.11
